HISTORY.rst
LICENSE
MANIFEST.in
README.rst
requirements.txt
setup.py
django_save_the_change.egg-info/PKG-INFO
django_save_the_change.egg-info/SOURCES.txt
django_save_the_change.egg-info/dependency_links.txt
django_save_the_change.egg-info/not-zip-safe
django_save_the_change.egg-info/requires.txt
django_save_the_change.egg-info/top_level.txt
save_the_change/__init__.py
save_the_change/mixins.py