Metadata-Version: 1.1
Name: django-save-the-change
Version: 1.0.0
Summary: Automatically save only changed model data.
Home-page: https://github.com/karanlyons/django-save-the-change
Author: Karan Lyons
Author-email: karan@karanlyons.com
License: Copyright 2013 Karan Lyons
